apxchangelog/.version
apxchangelog/__init__.py
apxchangelog/apxchangelog.py
apxchangelog/templates/changes.jinja2
apxchangelog/templates/commits_format.jinja2
apx_changelog-1.0.18.dist-info/LICENSE
apx_changelog-1.0.18.dist-info/METADATA
apx_changelog-1.0.18.dist-info/WHEEL
apx_changelog-1.0.18.dist-info/entry_points.txt
apx_changelog-1.0.18.dist-info/top_level.txt
apx_changelog-1.0.18.dist-info/RECORD
