Metadata-Version: 2.1
Name: apx-changelog
Version: 1.0.18
Summary: Generate changelog from a git repository
Home-page: https://github.com/uavos/apx-changelog
Author: Aliaksei Stratsiatau
Author-email: sa@uavos.com
License: MIT
Classifier: Development Status :: 5 - Production/Stable
Classifier: License :: OSI Approved :: MIT License
Classifier: Environment :: Console
Classifier: Natural Language :: English
Classifier: Programming Language :: Python :: 3
Classifier: Topic :: Software Development
Classifier: Topic :: Software Development :: Code Generators
Classifier: Intended Audience :: Developers
Requires-Python: >=3.5
License-File: LICENSE
Requires-Dist: regex
Requires-Dist: Jinja2
Requires-Dist: GitPython
